mlfix/__init__.py
mlfix/__main__.py
mlfix/cli.py
mlfix/fix.py
mlfix/path_utils.py
mlfix-0.0.1.dist-info/LICENSE
mlfix-0.0.1.dist-info/METADATA
mlfix-0.0.1.dist-info/WHEEL
mlfix-0.0.1.dist-info/entry_points.txt
mlfix-0.0.1.dist-info/top_level.txt
mlfix-0.0.1.dist-info/RECORD
