Metadata-Version: 2.1
Name: mlfix
Version: 0.0.1
Summary: mlflow artifact store migration fix tool
Home-page: https://github.com/konradmalik/mlfix.git
Author: Konrad Malik
Author-email: konrad.malik@gmail.com
License: MIT
Platform: UNKNOWN
Classifier: License :: OSI Approved :: MIT License
Classifier: Programming Language :: Python :: 3
Classifier: Programming Language :: Python :: 3.6
Classifier: Programming Language :: Python :: 3.7
Classifier: Programming Language :: Python :: 3.8
Classifier: Programming Language :: Python :: 3.9
Requires-Dist: pyyaml (==5.4.1)
